<?xml version='1.0' encoding='UTF-8'?>
<?artifactRepository version='1.1.0'?>
<repository name='AVR Eclipse Generate p2 Repository' type='org.eclipse.equinox.p2.artifact.repository.simpleRepository' version='1'>
  <properties size='3'>
    <property name='publishPackFilesAsSiblings' value='true'/>
    <property name='p2.compressed' value='true'/>
    <property name='p2.timestamp' value='1554810546608'/>
  </properties>
  <mappings size='5'>
    <rule filter='(&amp; (classifier=osgi.bundle) (format=packed))' output='${repoUrl}/plugins/${id}_${version}.jar.pack.gz'/>
    <rule filter='(&amp; (classifier=osgi.bundle))' output='${repoUrl}/plugins/${id}_${version}.jar'/>
    <rule filter='(&amp; (classifier=binary))' output='${repoUrl}/binary/${id}_${version}'/>
    <rule filter='(&amp; (classifier=org.eclipse.update.feature) (format=packed))' output='${repoUrl}/features/${id}_${version}.jar.pack.gz'/>
    <rule filter='(&amp; (classifier=org.eclipse.update.feature))' output='${repoUrl}/features/${id}_${version}.jar'/>
  </mappings>
  <artifacts size='7'>
    <artifact classifier='org.eclipse.update.feature' id='de.innot.avreclipse' version='2.5.2.20190409-1148-beta'>
      <properties size='9'>
        <property name='artifact.size' value='20376'/>
        <property name='download.size' value='20376'/>
        <property name='maven-groupId' value='avreclipse'/>
        <property name='maven-artifactId' value='de.innot.avreclipse'/>
        <property name='maven-version' value='2.5.2-SNAPSHOT'/>
        <property name='download.contentType' value='application/zip'/>
        <property name='download.md5' value='a5a58120a73cdd0a315ccca0b32779b3'/>
        <property name='download.checksum.md5' value='a5a58120a73cdd0a315ccca0b32779b3'/>
        <property name='download.checksum.sha-256' value='8578258218bb9e50a2e7c5a2ae0b124e63a607630f3c060487f7dedb7dad2b2b'/>
      </properties>
    </artifact>
    <artifact classifier='osgi.bundle' id='de.innot.avreclipse.core' version='2.5.2.20190409-1148-beta'>
      <properties size='8'>
        <property name='artifact.size' value='737416'/>
        <property name='download.size' value='737416'/>
        <property name='maven-groupId' value='avreclipse'/>
        <property name='maven-artifactId' value='de.innot.avreclipse.core'/>
        <property name='maven-version' value='2.5.2-SNAPSHOT'/>
        <property name='download.md5' value='a202a6558dd918a6ffd9e599f7ed77e1'/>
        <property name='download.checksum.md5' value='a202a6558dd918a6ffd9e599f7ed77e1'/>
        <property name='download.checksum.sha-256' value='03c97935d450ab11a835e5a92fe2dc96ce4a0a9c7f9cb09d88832440aa689b36'/>
      </properties>
    </artifact>
    <artifact classifier='osgi.bundle' id='de.innot.avreclipse.core.linux' version='2.5.2.20190409-1148-beta'>
      <properties size='8'>
        <property name='artifact.size' value='631366'/>
        <property name='download.size' value='631366'/>
        <property name='maven-groupId' value='avreclipse'/>
        <property name='maven-artifactId' value='de.innot.avreclipse.core.linux'/>
        <property name='maven-version' value='2.5.2-SNAPSHOT'/>
        <property name='download.md5' value='423724c68952a56a701aaf3dd1f0db71'/>
        <property name='download.checksum.md5' value='423724c68952a56a701aaf3dd1f0db71'/>
        <property name='download.checksum.sha-256' value='08f8df674f42052cbe6c073544f236ec5a7076b321571d40a0a908aa493d631a'/>
      </properties>
    </artifact>
    <artifact classifier='osgi.bundle' id='de.innot.avreclipse.doc' version='2.5.2.20190409-1148-beta'>
      <properties size='8'>
        <property name='artifact.size' value='1137064'/>
        <property name='download.size' value='1137064'/>
        <property name='maven-groupId' value='avreclipse'/>
        <property name='maven-artifactId' value='de.innot.avreclipse.doc'/>
        <property name='maven-version' value='2.5.2-SNAPSHOT'/>
        <property name='download.md5' value='4d437679babf4842b8a49365c9569704'/>
        <property name='download.checksum.md5' value='4d437679babf4842b8a49365c9569704'/>
        <property name='download.checksum.sha-256' value='ebb189de501d65215fbc5b1584564c0d10bf10b607352128e3c14d84a8630b8b'/>
      </properties>
    </artifact>
    <artifact classifier='osgi.bundle' id='de.innot.avreclipse.core.managedbuildsystem' version='2.5.2.20190409-1148-beta'>
      <properties size='8'>
        <property name='artifact.size' value='35611'/>
        <property name='download.size' value='35611'/>
        <property name='maven-groupId' value='avreclipse'/>
        <property name='maven-artifactId' value='de.innot.avreclipse.core.managedbuildsystem'/>
        <property name='maven-version' value='2.5.2-SNAPSHOT'/>
        <property name='download.md5' value='b04f16fb8b0194f954ca643c5fba0e10'/>
        <property name='download.checksum.md5' value='b04f16fb8b0194f954ca643c5fba0e10'/>
        <property name='download.checksum.sha-256' value='4a96373bfcb777818c5871a009266f4a1eea08830d106eae659c691ea38fa1d5'/>
      </properties>
    </artifact>
    <artifact classifier='osgi.bundle' id='de.innot.avreclipse.root' version='2.5.2.20190409-1148-beta'>
      <properties size='8'>
        <property name='artifact.size' value='5366'/>
        <property name='download.size' value='5366'/>
        <property name='maven-groupId' value='avreclipse'/>
        <property name='maven-artifactId' value='de.innot.avreclipse.root'/>
        <property name='maven-version' value='2.5.2-SNAPSHOT'/>
        <property name='download.md5' value='b61b6515c08dac462bbdcf38abf05bd0'/>
        <property name='download.checksum.md5' value='b61b6515c08dac462bbdcf38abf05bd0'/>
        <property name='download.checksum.sha-256' value='76334dd524c0a3bef43e313206dcceb24afb64421e4be63e6574fbd4e8c4032b'/>
      </properties>
    </artifact>
    <artifact classifier='osgi.bundle' id='de.innot.avreclipse.ui' version='2.5.2.20190409-1148-beta'>
      <properties size='8'>
        <property name='artifact.size' value='521320'/>
        <property name='download.size' value='521320'/>
        <property name='maven-groupId' value='avreclipse'/>
        <property name='maven-artifactId' value='de.innot.avreclipse.ui'/>
        <property name='maven-version' value='2.5.2-SNAPSHOT'/>
        <property name='download.md5' value='4f884400f8fd55a9a7f821c38d5f68fc'/>
        <property name='download.checksum.md5' value='4f884400f8fd55a9a7f821c38d5f68fc'/>
        <property name='download.checksum.sha-256' value='6a94b1ad1a0cbc64ec8e5dfff42d1c5d37b967a2c9220dde4242a6d2098a10d4'/>
      </properties>
    </artifact>
  </artifacts>
</repository>
